indenter/__init__.py
indenter/test_indent.py
indenter-1.0.2.dist-info/LICENSE
indenter-1.0.2.dist-info/METADATA
indenter-1.0.2.dist-info/WHEEL
indenter-1.0.2.dist-info/top_level.txt
indenter-1.0.2.dist-info/RECORD
