Metadata-Version: 2.1
Name: indenter
Version: 1.0.2
Summary: Programmatically indent output the right amount using `with`/`+`/`-`.
Home-page: https://github.com/glacials/indenter
Author: Ben Carlsson
Author-email: ben@twos.dev
License: MIT
Platform: any
Classifier: License :: OSI Approved :: MIT License
Classifier: Programming Language :: Python :: 3
Classifier: Programming Language :: Python :: 3.6
Classifier: Programming Language :: Python :: 3.7
Classifier: Programming Language :: Python :: 3.8
Classifier: Programming Language :: Python :: 3.9
Classifier: Programming Language :: Python :: 3.10
Classifier: Topic :: Software Development :: Libraries :: Python Modules
License-File: LICENSE
